{
  "doss": [
    {
      "id": "863f",
      "nomor": "4878",
      "nama": "Testguug",
      "email": "ddd@gmail.com",
      "kategori": "Siswa",
      "kelas": "X",
      "jurusan": "TKJ"
    },
    {
      "nama": "cocoopamm",
      "email": "hysaiiyaa@gmail.com",
      "kategori": "Siswa",
      "nomor": "23232313",
      "kelas": "XI",
      "jurusan": "TKJ",
      "id": "e195"
    },
    {
      "nama": "cocoopamm",
      "email": "hysaiiyaa@gmail.com",
      "kategori": "Siswa",
      "nomor": "1231232123",
      "kelas": "X",
      "jurusan": "TKJ",
      "id": "15dd"
    },
    {
      "id": "05f0",
      "nomor": "48783424234",
      "nama": "cocoopamm",
      "email": "hysaiiyaa@gmail.com",
      "kategori": "Siswa",
      "kelas": "X",
      "jurusan": "TSM"
    },
    {
      "nama": "Roihan ",
      "email": "roihan@gmail.com",
      "kategori": "Siswa",
      "nomor": "2589287447",
      "kelas": "XII",
      "jurusan": "TKJ",
      "id": "ec77"
    }
  ],
  "users": [
    {
      "id": "faac",
      "email": "hysaiiyaa@gmail.com",
      "password": "ww"
    },
    {
      "id": "8e8d",
      "email": "hysaiiyaa@gmail.com",
      "password": "jj"
    },
    {
      "id": "275f",
      "email": "hysaiiyaa@gmail.com",
      "password": "dswd"
    },
    {
      "id": "e527",
      "email": "hysaiiyaa@gmail.com",
      "password": "1234567"
    },
    {
      "id": "c445",
      "email": "hysaiiyaa@gmail.com",
      "password": "ds2qd"
    }
  ],
  "coco": [
    {
      "id": "f347",
      "nama": "cocoopamm",
      "email": "hysaiiyaa@gmail.com",
      "jumlah": 50000,
      "jenisTagihan": "SPP Bulanan",
      "tanggal": "2025-12-22",
      "status": "Belum Bayar"
    },
    {
      "id": "81f8",
      "nama": "Roihan ",
      "email": "roihan@gmail.com",
      "jumlah": "1000000",
      "jenisTagihan": "Outing Class 1",
      "tanggal": "2025-12-31",
      "status": "Sudah Bayar"
    }
  ],
  "kategori-data": [
    {
      "id": "0662",
      "nama_kategori": "SPP Bulanan",
      "keterangan": "Bayar uang sekolah perbulan",
      "aktif": true
    },
    {
      "id": "518b",
      "nama_kategori": "Seragam",
      "keterangan": " Seragam Sekolah ",
      "aktif": true
    },
    {
      "id": "a31a",
      "nama_kategori": "Uang Gedung",
      "keterangan": "Bayar uang sekolah perbulan",
      "aktif": true
    },
    {
      "id": "4ef0",
      "nama_kategori": "wdolpwkldpdw",
      "keterangan": "Program Belajar Di Luar",
      "aktif": false
    }
  ],
  "clok": [
    {
      "kategori_nama": "Siswa",
      "aktif": true,
      "id": "37fb"
    },
    {
      "kategori_nama": "Guru",
      "aktif": true,
      "id": "0265"
    },
    {
      "id": "18c6",
      "kategori_nama": "Karyawan",
      "aktif": true
    }
  ],
  "kls": [
    {
      "kelas": "X",
      "jurusan": "TKJ",
      "id": "5918"
    },
    {
      "kelas": "X",
      "jurusan": "TSM",
      "id": "8ef2"
    },
    {
      "kelas": "XI",
      "jurusan": "TKJ",
      "id": "a334"
    },
    {
      "kelas": "XI",
      "jurusan": "TSM",
      "id": "0d45"
    },
    {
      "kelas": "XII",
      "jurusan": "TKJ",
      "id": "ba6c"
    },
    {
      "kelas": "XII",
      "jurusan": "TSM",
      "id": "2ed2"
    },
    {
      "kelas": "X",
      "jurusan": "TKJ 3",
      "id": "4e3d"
    }
  ],
  "presensi": [
    {
      "id": "7116",
      "nis": "2589287447",
      "nama": "Roihan ",
      "tanggal": "2025-12-23",
      "jamMasuk": "12.29",
      "jamPulang": "12.29",
      "kehadiran": "HADIR",
      "keterangan": ""
    },
    {
      "id": "476d",
      "nis": "48783424234",
      "nama": "cocoopamm",
      "tanggal": "2025-12-23",
      "jamMasuk": "12.29",
      "jamPulang": "12.29",
      "kehadiran": "HADIR",
      "keterangan": ""
    },
    {
      "id": "e9d8",
      "nis": "2589287447",
      "nama": "Roihan ",
      "tanggal": "2026-01-15",
      "jamMasuk": "09:26",
      "jamPulang": "11:51",
      "kehadiran": "HADIR",
      "keterangan": ""
    }
  ]
}